ctCustomRedis/__init__.py
ctCustomRedis/redis.py
ctCustomRedis/redisConnection.py
ctCustomRedis/redisPool.py
ctCustomRedis-0.1.8.dist-info/METADATA
ctCustomRedis-0.1.8.dist-info/WHEEL
ctCustomRedis-0.1.8.dist-info/top_level.txt
ctCustomRedis-0.1.8.dist-info/RECORD
