Metadata-Version: 2.1
Name: ctCustomRedis
Version: 0.1.8
Summary: Common custom library for Redis
Home-page: UNKNOWN
Author: credenti
License: UNKNOWN
Platform: UNKNOWN
